maskingengine/__init__.py
maskingengine/config.py
maskingengine/detectors.py
maskingengine/masker.py
maskingengine/parsers.py
maskingengine/pattern_packs.py
maskingengine/rehydrator.py
maskingengine/sanitizer.py
maskingengine/api/__init__.py
maskingengine/api/main.py
maskingengine/cli/__init__.py
maskingengine/cli/main.py
maskingengine/core/__init__.py
maskingengine/core/config.schema.json
maskingengine/core/models.yaml
maskingengine/core/models_template.yaml
maskingengine/core/profiles.yaml
maskingengine/core/resolver.py
maskingengine/core/validator.py
maskingengine/pattern_packs/default.yaml
maskingengine/pattern_packs/template.yaml
maskingengine/pipeline/__init__.py
maskingengine/pipeline/streaming.py
maskingengine-1.2.0.dist-info/licenses/LICENSE
maskingengine-1.2.0.dist-info/METADATA
maskingengine-1.2.0.dist-info/WHEEL
maskingengine-1.2.0.dist-info/entry_points.txt
maskingengine-1.2.0.dist-info/top_level.txt
maskingengine-1.2.0.dist-info/RECORD
