Metadata-Version: 2.4
Name: maskingengine
Version: 1.2.0
Summary: Local-first PII redaction for LLM integration - mask before AI processing, restore after. Uses default patterns + multilingual NER, no network calls.
Home-page: https://github.com/foofork/maskingengine
Author: MaskingEngine Team
Author-email: MaskingEngine Team <contact@maskingengine.dev>
License: MIT License
Project-URL: Homepage, https://github.com/foofork/maskingengine
Project-URL: Documentation, https://github.com/foofork/maskingengine/blob/main/docs/README.md
Project-URL: Repository, https://github.com/foofork/maskingengine
Project-URL: Bug Tracker, https://github.com/foofork/maskingengine/issues
Keywords: pii,privacy,redaction,llm,openai,claude,gpt,langchain,local-first,multilingual,ner,regex,ai-pipelines
Classifier: Development Status :: 4 - Beta
Classifier: Intended Audience :: Developers
Classifier: Topic :: Software Development :: Libraries :: Python Modules
Classifier: Topic :: Security
Classifier: Topic :: Text Processing
Classifier: Programming Language :: Python :: 3
Classifier: Programming Language :: Python :: 3.8
Classifier: Programming Language :: Python :: 3.9
Classifier: Programming Language :: Python :: 3.10
Classifier: Programming Language :: Python :: 3.11
Classifier: Programming Language :: Python :: 3.12
Classifier: Operating System :: OS Independent
Requires-Python: >=3.8
License-File: LICENSE
Requires-Dist: pyyaml>=6.0
Requires-Dist: transformers>=4.21.0
Requires-Dist: torch>=1.12.0
Requires-Dist: click>=8.0.0
Requires-Dist: fastapi>=0.68.0
Requires-Dist: uvicorn>=0.15.0
Requires-Dist: pydantic>=1.8.0
Requires-Dist: requests>=2.25.0
Requires-Dist: jsonschema>=4.0.0
Provides-Extra: dev
Requires-Dist: pytest>=6.0; extra == "dev"
Requires-Dist: pytest-cov>=2.0; extra == "dev"
Requires-Dist: black>=21.0; extra == "dev"
Requires-Dist: flake8>=3.8; extra == "dev"
Requires-Dist: mypy>=0.910; extra == "dev"
Requires-Dist: pre-commit>=2.15; extra == "dev"
Requires-Dist: httpx>=0.23.0; extra == "dev"
Provides-Extra: api
Requires-Dist: fastapi>=0.68.0; extra == "api"
Requires-Dist: uvicorn>=0.15.0; extra == "api"
Requires-Dist: httpx>=0.23.0; extra == "api"
Provides-Extra: minimal
Requires-Dist: pyyaml>=6.0; extra == "minimal"
Requires-Dist: click>=8.0.0; extra == "minimal"
Dynamic: author
Dynamic: home-page
Dynamic: license-file
Dynamic: requires-python
